mpo_lab-0.1.1.dist-info/RECORD
mpo_lab-0.1.1.dist-info/top_level.txt
mpo_lab-0.1.1.dist-info/zip-safe
mpo_lab-0.1.1.dist-info/WHEEL
mpo_lab-0.1.1.dist-info/METADATA
mpo_lab-0.1.1.dist-info/LICENCE
mpo_lab/Matrix2MPO.cpython-37m-x86_64-linux-gnu.so
mpo_lab/MPOtorch.cpython-37m-x86_64-linux-gnu.so
