Metadata-Version: 2.1
Name: mpo-lab
Version: 0.1.1
Summary: Tools for model compression based on methods from paper, 'Enabling Lightweight Fine-tuning for Pre-trained Language Model Compression based on Matrix Product Operators'
Home-page: https://github.com/lpyhdzx/mpo_lab
Author: Peiyu Liu, Zefeng Gao
Author-email: liupeiyustu@163.com
License: MIT
Platform: UNKNOWN
Requires-Dist: numpy
Requires-Dist: torch
Requires-Dist: Cython
